docs/gen_doc.py
kmbbank/__init__.py
kmbbank/capcha_ocr.py
kmbbank/main.py
kmbbank/mbasync.py
kmbbank/wasm_helper/__init__.py
kmbbank/wasm_helper/helper.py
kmbbank-0.1.1.dist-info/licenses/LICENSE.txt
kmbbank-0.1.1.dist-info/licenses/NOTICE.txt
tests/async_test.py
tests/sync_test.py
kmbbank-0.1.1.dist-info/METADATA
kmbbank-0.1.1.dist-info/WHEEL
kmbbank-0.1.1.dist-info/top_level.txt
kmbbank-0.1.1.dist-info/RECORD
