Metadata-Version: 2.4
Name: kmbbank
Version: 0.1.1
Summary: Unofficial MB Bank client (repackaged as kmbbank).
Home-page: https://github.com/thedtvn/MBBank
Author: Lê Khang
Author-email: Lê Khang <kmb247.com@gmail.com>
License: MIT License
Project-URL: Homepage, https://kmb247.com
Project-URL: Source, https://github.com/thedtvn/MBBank
Project-URL: Issues, https://github.com/thedtvn/MBBank/issues
Keywords: mbbank,banking,api,unofficial
Classifier: Programming Language :: Python :: 3
Classifier: License :: OSI Approved :: MIT License
Classifier: Intended Audience :: Developers
Classifier: Topic :: Internet :: WWW/HTTP
Requires-Python: >=3.8
License-File: LICENSE.txt
License-File: NOTICE.txt
Requires-Dist: requests>=2.31.0
Requires-Dist: aiohttp
Requires-Dist: Pillow
Requires-Dist: wasmtime
Requires-Dist: mb-capcha-ocr>=0.1.5
Dynamic: author
Dynamic: home-page
Dynamic: license-file
Dynamic: requires-python
